{
  "$schema": "https://mintlify.com/docs.json",
  "name": "Upstash Redis Local",
  "theme": "aspen",
  "favicon": "https://media.brand.dev/7d108835-69f7-4a45-9110-a9491bb3a839.png",
  "logo": {
    "light": "https://media.brand.dev/a5c1d954-f019-4984-a018-9311563f59d9.svg",
    "dark": "https://media.brand.dev/a5c1d954-f019-4984-a018-9311563f59d9.svg"
  },
  "colors": {
    "primary": "#65eac2",
    "light": "#647c7c",
    "dark": "#040605"
  },
  "navbar": {
    "primary": {
      "type": "github",
      "href": "https://github.com/aine1100/Upstash-Redis-Local-server"
    }
  },
  "navigation": {
    "tabs": [
      {
        "tab": "Documentation",
        "groups": [
          {
            "group": "Get Started",
            "pages": [
              "introduction",
              "quickstart",
              "installation"
            ]
          },
          {
            "group": "Core Concepts",
            "pages": [
              "concepts/how-it-works",
              "concepts/authentication",
              "concepts/docker-profiles"
            ]
          },
          {
            "group": "Guides",
            "pages": [
              "guides/upstash-redis-sdk",
              "guides/dashboard",
              "guides/rate-limit-simulation",
              "guides/data-management",
              "guides/qstash",
              "guides/testing-tools"
            ]
          },
          {
            "group": "Configuration",
            "pages": [
              "configuration/server-options",
              "configuration/environment-variables",
              "configuration/security"
            ]
          },
          {
            "group": "Troubleshooting",
            "pages": [
              "troubleshooting/common-issues",
              "troubleshooting/faq"
            ]
          }
        ]
      },
      {
        "tab": "API Reference",
        "groups": [
          {
            "group": "REST API",
            "pages": [
              "api/overview",
              "api/commands",
              "api/pipeline",
              "api/pubsub"
            ]
          },
          {
            "group": "CLI",
            "pages": [
              "cli/overview",
              "cli/commands"
            ]
          }
        ]
      }
    ]
  }
}
